<file_info>
   <name><OUTFILE_1/>.zip</name>
   <generated_locally/>
   <upload_when_present/>
   <max_nbytes>50000000</max_nbytes>
   <url>http://qcn-upl.stanford.edu/qcn_cgi/file_upload_handler</url>
</file_info>
<file_info>
   <name><OUTFILE_2/>.zip</name>
   <generated_locally/>
   <upload_when_present/>
   <max_nbytes>50000000</max_nbytes>
   <url>http://qcn-upl.stanford.edu/qcn_cgi/file_upload_handler</url>
</file_info>
<file_info>
   <name><OUTFILE_3/>.zip</name>
   <generated_locally/>
   <upload_when_present/>
   <max_nbytes>50000000</max_nbytes>
   <url>http://qcn-upl.stanford.edu/qcn_cgi/file_upload_handler</url>
</file_info>
<file_info>
   <name><OUTFILE_4/>.zip</name>
   <generated_locally/>
   <upload_when_present/>
   <max_nbytes>50000000</max_nbytes>
   <url>http://qcn-upl.stanford.edu/qcn_cgi/file_upload_handler</url>
</file_info>
<file_info>
   <name><OUTFILE_5/>.zip</name>
   <generated_locally/>
   <upload_when_present/>
   <max_nbytes>50000000</max_nbytes>
   <url>http://qcn-upl.stanford.edu/qcn_cgi/file_upload_handler</url>
</file_info>
<file_info>
   <name><OUTFILE_6/>.zip</name>
   <generated_locally/>
   <upload_when_present/>
   <max_nbytes>50000000</max_nbytes>
   <url>http://qcn-upl.stanford.edu/qcn_cgi/file_upload_handler</url>
</file_info>
<file_info>
   <name><OUTFILE_7/>.zip</name>
   <generated_locally/>
   <upload_when_present/>
   <max_nbytes>50000000</max_nbytes>
   <url>http://qcn-upl.stanford.edu/qcn_cgi/file_upload_handler</url>
</file_info>
<file_info>
   <name><OUTFILE_8/>.zip</name>
   <generated_locally/>
   <upload_when_present/>
   <max_nbytes>50000000</max_nbytes>
   <url>http://qcn-upl.stanford.edu/qcn_cgi/file_upload_handler</url>
</file_info>
<file_info>
   <name><OUTFILE_9/>.zip</name>
   <generated_locally/>
   <upload_when_present/>
   <max_nbytes>50000000</max_nbytes>
   <url>http://qcn-upl.stanford.edu/qcn_cgi/file_upload_handler</url>
</file_info>
<file_info>
   <name><OUTFILE_10/>.zip</name>
   <generated_locally/>
   <upload_when_present/>
   <max_nbytes>50000000</max_nbytes>
   <url>http://qcn-upl.stanford.edu/qcn_cgi/file_upload_handler</url>
</file_info>
<file_info>
   <name><OUTFILE_11/>.zip</name>
   <generated_locally/>
   <upload_when_present/>
   <max_nbytes>50000000</max_nbytes>
   <url>http://qcn-upl.stanford.edu/qcn_cgi/file_upload_handler</url>
</file_info>
<file_info>
   <name><OUTFILE_12/>.zip</name>
   <generated_locally/>
   <upload_when_present/>
   <max_nbytes>50000000</max_nbytes>
   <url>http://qcn-upl.stanford.edu/qcn_cgi/file_upload_handler</url>
</file_info>
<file_info>
   <name><OUTFILE_13/>.zip</name>
   <generated_locally/>
   <upload_when_present/>
   <max_nbytes>50000000</max_nbytes>
   <url>http://qcn-upl.stanford.edu/qcn_cgi/file_upload_handler</url>
</file_info>
<file_info>
   <name><OUTFILE_14/>.zip</name>
   <generated_locally/>
   <upload_when_present/>
   <max_nbytes>50000000</max_nbytes>
   <url>http://qcn-upl.stanford.edu/qcn_cgi/file_upload_handler</url>
</file_info>
<file_info>
   <name><OUTFILE_15/>.zip</name>
   <generated_locally/>
   <upload_when_present/>
   <max_nbytes>50000000</max_nbytes>
   <url>http://qcn-upl.stanford.edu/qcn_cgi/file_upload_handler</url>
</file_info>
<file_info>
   <name><OUTFILE_16/>.zip</name>
   <generated_locally/>
   <upload_when_present/>
   <max_nbytes>50000000</max_nbytes>
   <url>http://qcn-upl.stanford.edu/qcn_cgi/file_upload_handler</url>
</file_info>
<file_info>
   <name><OUTFILE_17/>.zip</name>
   <generated_locally/>
   <upload_when_present/>
   <max_nbytes>50000000</max_nbytes>
   <url>http://qcn-upl.stanford.edu/qcn_cgi/file_upload_handler</url>
</file_info>
<file_info>
   <name><OUTFILE_18/>.zip</name>
   <generated_locally/>
   <upload_when_present/>
   <max_nbytes>50000000</max_nbytes>
   <url>http://qcn-upl.stanford.edu/qcn_cgi/file_upload_handler</url>
</file_info>
<file_info>
   <name><OUTFILE_19/>.zip</name>
   <generated_locally/>
   <upload_when_present/>
   <max_nbytes>50000000</max_nbytes>
   <url>http://qcn-upl.stanford.edu/qcn_cgi/file_upload_handler</url>
</file_info>
<file_info>
   <name><OUTFILE_20/>.zip</name>
   <generated_locally/>
   <upload_when_present/>
   <max_nbytes>50000000</max_nbytes>
   <url>http://qcn-upl.stanford.edu/qcn_cgi/file_upload_handler</url>
</file_info>
<file_info>
   <name><OUTFILE_21/>.zip</name>
   <generated_locally/>
   <upload_when_present/>
   <max_nbytes>50000000</max_nbytes>
   <url>http://qcn-upl.stanford.edu/qcn_cgi/file_upload_handler</url>
</file_info>
<file_info>
   <name><OUTFILE_22/>.zip</name>
   <generated_locally/>
   <upload_when_present/>
   <max_nbytes>50000000</max_nbytes>
   <url>http://qcn-upl.stanford.edu/qcn_cgi/file_upload_handler</url>
</file_info>
<file_info>
   <name><OUTFILE_23/>.zip</name>
   <generated_locally/>
   <upload_when_present/>
   <max_nbytes>50000000</max_nbytes>
   <url>http://qcn-upl.stanford.edu/qcn_cgi/file_upload_handler</url>
</file_info>
<file_info>
   <name><OUTFILE_24/>.zip</name>
   <generated_locally/>
   <upload_when_present/>
   <max_nbytes>50000000</max_nbytes>
   <url>http://qcn-upl.stanford.edu/qcn_cgi/file_upload_handler</url>
</file_info>
<file_info>
   <name><OUTFILE_25/>.zip</name>
   <generated_locally/>
   <upload_when_present/>
   <max_nbytes>50000000</max_nbytes>
   <url>http://qcn-upl.stanford.edu/qcn_cgi/file_upload_handler</url>
</file_info>
<file_info>
   <name><OUTFILE_26/>.zip</name>
   <generated_locally/>
   <upload_when_present/>
   <max_nbytes>50000000</max_nbytes>
   <url>http://qcn-upl.stanford.edu/qcn_cgi/file_upload_handler</url>
</file_info>
<file_info>
   <name><OUTFILE_27/>.zip</name>
   <generated_locally/>
   <upload_when_present/>
   <max_nbytes>50000000</max_nbytes>
   <url>http://qcn-upl.stanford.edu/qcn_cgi/file_upload_handler</url>
</file_info>
<file_info>
   <name><OUTFILE_28/>.zip</name>
   <generated_locally/>
   <upload_when_present/>
   <max_nbytes>50000000</max_nbytes>
   <url>http://qcn-upl.stanford.edu/qcn_cgi/file_upload_handler</url>
</file_info>
<file_info>
   <name><OUTFILE_29/>.zip</name>
   <generated_locally/>
   <upload_when_present/>
   <max_nbytes>50000000</max_nbytes>
   <url>http://qcn-upl.stanford.edu/qcn_cgi/file_upload_handler</url>
</file_info>
<file_info>
   <name><OUTFILE_30/>.zip</name>
   <generated_locally/>
   <upload_when_present/>
   <max_nbytes>50000000</max_nbytes>
   <url>http://qcn-upl.stanford.edu/qcn_cgi/file_upload_handler</url>
</file_info>
<file_info>
   <name><OUTFILE_31/>.zip</name>
   <generated_locally/>
   <upload_when_present/>
   <max_nbytes>50000000</max_nbytes>
   <url>http://qcn-upl.stanford.edu/qcn_cgi/file_upload_handler</url>
</file_info>
<file_info>
   <name><OUTFILE_32/>.zip</name>
   <generated_locally/>
   <upload_when_present/>
   <max_nbytes>50000000</max_nbytes>
   <url>http://qcn-upl.stanford.edu/qcn_cgi/file_upload_handler</url>
</file_info>
<file_info>
   <name><OUTFILE_33/>.zip</name>
   <generated_locally/>
   <upload_when_present/>
   <max_nbytes>50000000</max_nbytes>
   <url>http://qcn-upl.stanford.edu/qcn_cgi/file_upload_handler</url>
</file_info>
<file_info>
   <name><OUTFILE_34/>.zip</name>
   <generated_locally/>
   <upload_when_present/>
   <max_nbytes>50000000</max_nbytes>
   <url>http://qcn-upl.stanford.edu/qcn_cgi/file_upload_handler</url>
</file_info>
<file_info>
   <name><OUTFILE_35/>.zip</name>
   <generated_locally/>
   <upload_when_present/>
   <max_nbytes>50000000</max_nbytes>
   <url>http://qcn-upl.stanford.edu/qcn_cgi/file_upload_handler</url>
</file_info>
<file_info>
   <name><OUTFILE_36/>.zip</name>
   <generated_locally/>
   <upload_when_present/>
   <max_nbytes>50000000</max_nbytes>
   <url>http://qcn-upl.stanford.edu/qcn_cgi/file_upload_handler</url>
</file_info>
<file_info>
   <name><OUTFILE_37/>.zip</name>
   <generated_locally/>
   <upload_when_present/>
   <max_nbytes>50000000</max_nbytes>
   <url>http://qcn-upl.stanford.edu/qcn_cgi/file_upload_handler</url>
</file_info>
<file_info>
   <name><OUTFILE_38/>.zip</name>
   <generated_locally/>
   <upload_when_present/>
   <max_nbytes>50000000</max_nbytes>
   <url>http://qcn-upl.stanford.edu/qcn_cgi/file_upload_handler</url>
</file_info>
<file_info>
   <name><OUTFILE_39/>.zip</name>
   <generated_locally/>
   <upload_when_present/>
   <max_nbytes>50000000</max_nbytes>
   <url>http://qcn-upl.stanford.edu/qcn_cgi/file_upload_handler</url>
</file_info>
<file_info>
   <name><OUTFILE_40/>.zip</name>
   <generated_locally/>
   <upload_when_present/>
   <max_nbytes>50000000</max_nbytes>
   <url>http://qcn-upl.stanford.edu/qcn_cgi/file_upload_handler</url>
</file_info>
<file_info>
   <name><OUTFILE_41/>.zip</name>
   <generated_locally/>
   <upload_when_present/>
   <max_nbytes>50000000</max_nbytes>
   <url>http://qcn-upl.stanford.edu/qcn_cgi/file_upload_handler</url>
</file_info>
<file_info>
   <name><OUTFILE_42/>.zip</name>
   <generated_locally/>
   <upload_when_present/>
   <max_nbytes>50000000</max_nbytes>
   <url>http://qcn-upl.stanford.edu/qcn_cgi/file_upload_handler</url>
</file_info>
<file_info>
   <name><OUTFILE_43/>.zip</name>
   <generated_locally/>
   <upload_when_present/>
   <max_nbytes>50000000</max_nbytes>
   <url>http://qcn-upl.stanford.edu/qcn_cgi/file_upload_handler</url>
</file_info>
<file_info>
   <name><OUTFILE_44/>.zip</name>
   <generated_locally/>
   <upload_when_present/>
   <max_nbytes>50000000</max_nbytes>
   <url>http://qcn-upl.stanford.edu/qcn_cgi/file_upload_handler</url>
</file_info>
<file_info>
   <name><OUTFILE_45/>.zip</name>
   <generated_locally/>
   <upload_when_present/>
   <max_nbytes>50000000</max_nbytes>
   <url>http://qcn-upl.stanford.edu/qcn_cgi/file_upload_handler</url>
</file_info>
<file_info>
   <name><OUTFILE_46/>.zip</name>
   <generated_locally/>
   <upload_when_present/>
   <max_nbytes>50000000</max_nbytes>
   <url>http://qcn-upl.stanford.edu/qcn_cgi/file_upload_handler</url>
</file_info>
<file_info>
   <name><OUTFILE_47/>.zip</name>
   <generated_locally/>
   <upload_when_present/>
   <max_nbytes>50000000</max_nbytes>
   <url>http://qcn-upl.stanford.edu/qcn_cgi/file_upload_handler</url>
</file_info>
<file_info>
   <name><OUTFILE_48/>.zip</name>
   <generated_locally/>
   <upload_when_present/>
   <max_nbytes>50000000</max_nbytes>
   <url>http://qcn-upl.stanford.edu/qcn_cgi/file_upload_handler</url>
</file_info>
<file_info>
   <name><OUTFILE_49/>.zip</name>
   <generated_locally/>
   <upload_when_present/>
   <max_nbytes>50000000</max_nbytes>
   <url>http://qcn-upl.stanford.edu/qcn_cgi/file_upload_handler</url>
</file_info>
<file_info>
   <name><OUTFILE_50/>.zip</name>
   <generated_locally/>
   <upload_when_present/>
   <max_nbytes>50000000</max_nbytes>
   <url>http://qcn-upl.stanford.edu/qcn_cgi/file_upload_handler</url>
</file_info>
<result>
  <file_ref>
     <file_name><OUTFILE_1/>.zip</file_name>
     <open_name>qcnout1.zip</open_name>
     <optional>1</optional>
     <no_validate>1</no_validate>
  </file_ref>
  <file_ref>
     <file_name><OUTFILE_2/>.zip</file_name>
     <open_name>qcnout2.zip</open_name>
     <optional>1</optional>
     <no_validate>1</no_validate>
  </file_ref>
  <file_ref>
     <file_name><OUTFILE_3/>.zip</file_name>
     <open_name>qcnout3.zip</open_name>
     <optional>1</optional>
     <no_validate>1</no_validate>
  </file_ref>
  <file_ref>
     <file_name><OUTFILE_4/>.zip</file_name>
     <open_name>qcnout4.zip</open_name>
     <optional>1</optional>
     <no_validate>1</no_validate>
  </file_ref>
  <file_ref>
     <file_name><OUTFILE_5/>.zip</file_name>
     <open_name>qcnout5.zip</open_name>
     <optional>1</optional>
     <no_validate>1</no_validate>
  </file_ref>
  <file_ref>
     <file_name><OUTFILE_6/>.zip</file_name>
     <open_name>qcnout6.zip</open_name>
     <optional>1</optional>
     <no_validate>1</no_validate>
  </file_ref>
  <file_ref>
     <file_name><OUTFILE_7/>.zip</file_name>
     <open_name>qcnout7.zip</open_name>
     <optional>1</optional>
     <no_validate>1</no_validate>
  </file_ref>
  <file_ref>
     <file_name><OUTFILE_8/>.zip</file_name>
     <open_name>qcnout8.zip</open_name>
     <optional>1</optional>
     <no_validate>1</no_validate>
  </file_ref>
  <file_ref>
     <file_name><OUTFILE_9/>.zip</file_name>
     <open_name>qcnout9.zip</open_name>
     <optional>1</optional>
     <no_validate>1</no_validate>
  </file_ref>
  <file_ref>
     <file_name><OUTFILE_10/>.zip</file_name>
     <open_name>qcnout10.zip</open_name>
     <optional>1</optional>
     <no_validate>1</no_validate>
  </file_ref>
  <file_ref>
     <file_name><OUTFILE_11/>.zip</file_name>
     <open_name>qcnout11.zip</open_name>
     <optional>1</optional>
     <no_validate>1</no_validate>
  </file_ref>
  <file_ref>
     <file_name><OUTFILE_12/>.zip</file_name>
     <open_name>qcnout12.zip</open_name>
     <optional>1</optional>
     <no_validate>1</no_validate>
  </file_ref>
  <file_ref>
     <file_name><OUTFILE_13/>.zip</file_name>
     <open_name>qcnout13.zip</open_name>
     <optional>1</optional>
     <no_validate>1</no_validate>
  </file_ref>
  <file_ref>
     <file_name><OUTFILE_14/>.zip</file_name>
     <open_name>qcnout14.zip</open_name>
     <optional>1</optional>
     <no_validate>1</no_validate>
  </file_ref>
  <file_ref>
     <file_name><OUTFILE_15/>.zip</file_name>
     <open_name>qcnout15.zip</open_name>
     <optional>1</optional>
     <no_validate>1</no_validate>
  </file_ref>
  <file_ref>
     <file_name><OUTFILE_16/>.zip</file_name>
     <open_name>qcnout16.zip</open_name>
     <optional>1</optional>
     <no_validate>1</no_validate>
  </file_ref>
  <file_ref>
     <file_name><OUTFILE_17/>.zip</file_name>
     <open_name>qcnout17.zip</open_name>
     <optional>1</optional>
     <no_validate>1</no_validate>
  </file_ref>
  <file_ref>
     <file_name><OUTFILE_18/>.zip</file_name>
     <open_name>qcnout18.zip</open_name>
     <optional>1</optional>
     <no_validate>1</no_validate>
  </file_ref>
  <file_ref>
     <file_name><OUTFILE_19/>.zip</file_name>
     <open_name>qcnout19.zip</open_name>
     <optional>1</optional>
     <no_validate>1</no_validate>
  </file_ref>
  <file_ref>
     <file_name><OUTFILE_20/>.zip</file_name>
     <open_name>qcnout20.zip</open_name>
     <optional>1</optional>
     <no_validate>1</no_validate>
  </file_ref>
  <file_ref>
     <file_name><OUTFILE_21/>.zip</file_name>
     <open_name>qcnout21.zip</open_name>
     <optional>1</optional>
     <no_validate>1</no_validate>
  </file_ref>
  <file_ref>
     <file_name><OUTFILE_22/>.zip</file_name>
     <open_name>qcnout22.zip</open_name>
     <optional>1</optional>
     <no_validate>1</no_validate>
  </file_ref>
  <file_ref>
     <file_name><OUTFILE_23/>.zip</file_name>
     <open_name>qcnout23.zip</open_name>
     <optional>1</optional>
     <no_validate>1</no_validate>
  </file_ref>
  <file_ref>
     <file_name><OUTFILE_24/>.zip</file_name>
     <open_name>qcnout24.zip</open_name>
     <optional>1</optional>
     <no_validate>1</no_validate>
  </file_ref>
  <file_ref>
     <file_name><OUTFILE_25/>.zip</file_name>
     <open_name>qcnout25.zip</open_name>
     <optional>1</optional>
     <no_validate>1</no_validate>
  </file_ref>
  <file_ref>
     <file_name><OUTFILE_26/>.zip</file_name>
     <open_name>qcnout26.zip</open_name>
     <optional>1</optional>
     <no_validate>1</no_validate>
  </file_ref>
  <file_ref>
     <file_name><OUTFILE_27/>.zip</file_name>
     <open_name>qcnout27.zip</open_name>
     <optional>1</optional>
     <no_validate>1</no_validate>
  </file_ref>
  <file_ref>
     <file_name><OUTFILE_28/>.zip</file_name>
     <open_name>qcnout28.zip</open_name>
     <optional>1</optional>
     <no_validate>1</no_validate>
  </file_ref>
  <file_ref>
     <file_name><OUTFILE_29/>.zip</file_name>
     <open_name>qcnout29.zip</open_name>
     <optional>1</optional>
     <no_validate>1</no_validate>
  </file_ref>
  <file_ref>
     <file_name><OUTFILE_30/>.zip</file_name>
     <open_name>qcnout30.zip</open_name>
     <optional>1</optional>
     <no_validate>1</no_validate>
  </file_ref>
  <file_ref>
     <file_name><OUTFILE_31/>.zip</file_name>
     <open_name>qcnout31.zip</open_name>
     <optional>1</optional>
     <no_validate>1</no_validate>
  </file_ref>
  <file_ref>
     <file_name><OUTFILE_32/>.zip</file_name>
     <open_name>qcnout32.zip</open_name>
     <optional>1</optional>
     <no_validate>1</no_validate>
  </file_ref>
  <file_ref>
     <file_name><OUTFILE_33/>.zip</file_name>
     <open_name>qcnout33.zip</open_name>
     <optional>1</optional>
     <no_validate>1</no_validate>
  </file_ref>
  <file_ref>
     <file_name><OUTFILE_34/>.zip</file_name>
     <open_name>qcnout34.zip</open_name>
     <optional>1</optional>
     <no_validate>1</no_validate>
  </file_ref>
  <file_ref>
     <file_name><OUTFILE_35/>.zip</file_name>
     <open_name>qcnout35.zip</open_name>
     <optional>1</optional>
     <no_validate>1</no_validate>
  </file_ref>
  <file_ref>
     <file_name><OUTFILE_36/>.zip</file_name>
     <open_name>qcnout36.zip</open_name>
     <optional>1</optional>
     <no_validate>1</no_validate>
  </file_ref>
  <file_ref>
     <file_name><OUTFILE_37/>.zip</file_name>
     <open_name>qcnout37.zip</open_name>
     <optional>1</optional>
     <no_validate>1</no_validate>
  </file_ref>
  <file_ref>
     <file_name><OUTFILE_38/>.zip</file_name>
     <open_name>qcnout38.zip</open_name>
     <optional>1</optional>
     <no_validate>1</no_validate>
  </file_ref>
  <file_ref>
     <file_name><OUTFILE_39/>.zip</file_name>
     <open_name>qcnout39.zip</open_name>
     <optional>1</optional>
     <no_validate>1</no_validate>
  </file_ref>
  <file_ref>
     <file_name><OUTFILE_40/>.zip</file_name>
     <open_name>qcnout40.zip</open_name>
     <optional>1</optional>
     <no_validate>1</no_validate>
  </file_ref>
  <file_ref>
     <file_name><OUTFILE_41/>.zip</file_name>
     <open_name>qcnout41.zip</open_name>
     <optional>1</optional>
     <no_validate>1</no_validate>
  </file_ref>
  <file_ref>
     <file_name><OUTFILE_42/>.zip</file_name>
     <open_name>qcnout42.zip</open_name>
     <optional>1</optional>
     <no_validate>1</no_validate>
  </file_ref>
  <file_ref>
     <file_name><OUTFILE_43/>.zip</file_name>
     <open_name>qcnout43.zip</open_name>
     <optional>1</optional>
     <no_validate>1</no_validate>
  </file_ref>
  <file_ref>
     <file_name><OUTFILE_44/>.zip</file_name>
     <open_name>qcnout44.zip</open_name>
     <optional>1</optional>
     <no_validate>1</no_validate>
  </file_ref>
  <file_ref>
     <file_name><OUTFILE_45/>.zip</file_name>
     <open_name>qcnout45.zip</open_name>
     <optional>1</optional>
     <no_validate>1</no_validate>
  </file_ref>
  <file_ref>
     <file_name><OUTFILE_46/>.zip</file_name>
     <open_name>qcnout46.zip</open_name>
     <optional>1</optional>
     <no_validate>1</no_validate>
  </file_ref>
  <file_ref>
     <file_name><OUTFILE_47/>.zip</file_name>
     <open_name>qcnout47.zip</open_name>
     <optional>1</optional>
     <no_validate>1</no_validate>
  </file_ref>
  <file_ref>
     <file_name><OUTFILE_48/>.zip</file_name>
     <open_name>qcnout48.zip</open_name>
     <optional>1</optional>
     <no_validate>1</no_validate>
  </file_ref>
  <file_ref>
     <file_name><OUTFILE_49/>.zip</file_name>
     <open_name>qcnout49.zip</open_name>
     <optional>1</optional>
     <no_validate>1</no_validate>
  </file_ref>
  <file_ref>
     <file_name><OUTFILE_50/>.zip</file_name>
     <open_name>qcnout50.zip</open_name>
     <optional>1</optional>
     <no_validate>1</no_validate>
  </file_ref>
</result>
